sleepkit/__init__.py
sleepkit/__main__.py
sleepkit/cli.py
sleepkit/defines.py
sleepkit/backends/__init__.py
sleepkit/backends/backend.py
sleepkit/backends/evb.py
sleepkit/backends/pc.py
sleepkit/backends/utils.py
sleepkit/backends/GenericDataOperations_EvbToPc/__init__.py
sleepkit/backends/GenericDataOperations_EvbToPc/client.py
sleepkit/backends/GenericDataOperations_EvbToPc/common.py
sleepkit/backends/GenericDataOperations_EvbToPc/interface.py
sleepkit/backends/GenericDataOperations_EvbToPc/server.py
sleepkit/backends/GenericDataOperations_PcToEvb/__init__.py
sleepkit/backends/GenericDataOperations_PcToEvb/client.py
sleepkit/backends/GenericDataOperations_PcToEvb/common.py
sleepkit/backends/GenericDataOperations_PcToEvb/interface.py
sleepkit/backends/GenericDataOperations_PcToEvb/server.py
sleepkit/backends/erpc/__init__.py
sleepkit/backends/erpc/arbitrator.py
sleepkit/backends/erpc/basic_codec.py
sleepkit/backends/erpc/client.py
sleepkit/backends/erpc/codec.py
sleepkit/backends/erpc/crc16.py
sleepkit/backends/erpc/erpc_version.py
sleepkit/backends/erpc/server.py
sleepkit/backends/erpc/simple_server.py
sleepkit/backends/erpc/transport.py
sleepkit/datasets/__init__.py
sleepkit/datasets/augmentation.py
sleepkit/datasets/cmidss.py
sleepkit/datasets/dataset.py
sleepkit/datasets/defines.py
sleepkit/datasets/mesa.py
sleepkit/datasets/nsrr.py
sleepkit/datasets/stages.py
sleepkit/datasets/ysyw.py
sleepkit/features/__init__.py
sleepkit/features/featureset.py
sleepkit/features/fs_c_ear_9.py
sleepkit/features/fs_h_e_10.py
sleepkit/features/fs_w_a_5.py
sleepkit/features/fs_w_p_40.py
sleepkit/features/fs_w_p_5.py
sleepkit/features/fs_w_pa_14.py
sleepkit/features/h5dataloader.py
sleepkit/models/__init__.py
sleepkit/tasks/__init__.py
sleepkit/tasks/task.py
sleepkit/tasks/apnea/__init__.py
sleepkit/tasks/apnea/demo.py
sleepkit/tasks/apnea/evaluate.py
sleepkit/tasks/apnea/export.py
sleepkit/tasks/apnea/metrics.py
sleepkit/tasks/apnea/train.py
sleepkit/tasks/apnea/utils.py
sleepkit-0.11.1.dist-info/licenses/LICENSE
sleepkit-0.11.1.dist-info/METADATA
sleepkit-0.11.1.dist-info/WHEEL
sleepkit-0.11.1.dist-info/entry_points.txt
sleepkit-0.11.1.dist-info/top_level.txt
sleepkit-0.11.1.dist-info/RECORD
