Metadata-Version: 2.4
Name: sleepkit
Version: 0.11.1
Summary: AI driven sleep monitoring kit for ultra low-power wearables.
Author-email: Ambiq AI <support.aitg@ambiq.com>
License: BSD-3-Clause
Requires-Python: <3.14,>=3.12
License-File: LICENSE
Requires-Dist: tensorflow<3.0,>=2.20.0
Requires-Dist: tensorflow-metal<2.0,>=1.1.0; sys_platform == "darwin"
Requires-Dist: numpy<3.0,>=2.1.0
Requires-Dist: scikit-learn<2.0,>=1.4.0
Requires-Dist: wfdb<5.0,>=4.1.2
Requires-Dist: fastparquet<2024.0,>=2023.10.1
Requires-Dist: plotly<6.0,>=5.18.0
Requires-Dist: tqdm<5.0,>=4.66.1
Requires-Dist: seaborn<1.0,>=0.13.2
Requires-Dist: matplotlib<4.0,>=3.9.0
Requires-Dist: pydantic<3.0,>=2.5.3
Requires-Dist: pyserial<4.0,>=3.5
Requires-Dist: rich<14.0,>=13.7.0
Requires-Dist: wandb<1.0,>=0.17.0
Requires-Dist: scipy<2.0,>=1.12.0
Requires-Dist: boto3<2.0,>=1.34.36
Requires-Dist: orjson<4.0,>=3.9.13
Requires-Dist: physiokit<1.0,>=0.10.1
Requires-Dist: requests<3.0,>=2.31.0
Requires-Dist: argdantic[all]<2.0,>=1.0.0
Requires-Dist: h5py>=3.13.0
Requires-Dist: pyedflib>=0.1.40
Requires-Dist: kaggle>=1.7.4.5
Requires-Dist: helia-edge>=0.4.1
Dynamic: license-file
